pytest_axe/__init__.py
pytest_axe/parameterize_tests.py
pytest_axe/pytest_axe.py
pytest_axe-1.1.6.dist-info/METADATA
pytest_axe-1.1.6.dist-info/RECORD
pytest_axe-1.1.6.dist-info/WHEEL
pytest_axe-1.1.6.dist-info/entry_points.txt
pytest_axe-1.1.6.dist-info/top_level.txt
