Metadata-Version: 2.1
Name: pytest-axe
Version: 1.1.6
Summary: pytest plugin for axe-selenium-python
Home-page: http://github.com/kimberlythegeek/pytest-axe
Author: Kimberly Sereduck
Author-email: ksereduck@mozilla.com
License: Mozilla Public License 2.0 (MPL 2.0)
Keywords: axe-core selenium pytest-selenium accessibility automation mozilla
Platform: UNKNOWN
Requires-Dist: pytest-selenium (>=1.12.0)
Requires-Dist: pytest (>=3.0.0)
Requires-Dist: axe-selenium-python (==2.1.5)
